<?xml version="1.0" encoding="utf-8" ?>
<dwsync>
<file name="AdminWebsitesController.php" server="192.168.1.235//var/www/html/jili-amy/" local="130416928848243608" remote="130416934780000000" Dst="0" />
<file name="ApiController.php" server="192.168.1.235//var/www/html/jili-amy/" local="130415221383125939" remote="130415226690000000" Dst="0" />
<file name="HotactivityController.php" server="192.168.1.235//var/www/html/jili-amy/" local="130416928848323613" remote="130416934780000000" Dst="0" />
<file name="ProductController.php" server="192.168.1.235//var/www/html/jili-amy/" local="130416928848353615" remote="130416934780000000" Dst="0" />
<file name="SearchController.php" server="192.168.1.235//var/www/html/jili-amy/" local="130415221383265947" remote="130415226690000000" Dst="0" />
<file name="TopController.php" server="192.168.1.235//var/www/html/jili-amy/" local="130416746084750134" remote="130416752050000000" Dst="0" />
<file name="AdminEmarWebsitesCronedController.php" server="192.168.1.235//var/www/html/jili-amy/" local="130416928848213607" remote="130416934780000000" Dst="0" />
<file name="GhsController.php" server="192.168.1.235//var/www/html/jili-amy/" local="130416928848293611" remote="130416934780000000" Dst="0" />
<file name="WebsitesController.php" server="192.168.1.235//var/www/html/jili-amy/" local="130416928848383616" remote="130416934780000000" Dst="0" />
<file name="AnalogController.php" server="192.168.1.235//var/www/html/jili-amy/" local="130416928848263609" remote="130416934780000000" Dst="0" />
</dwsync>