<?xml version="1.0" encoding="utf-8" ?>
<dwsync>
<file name="advertiserment.png" server="192.168.1.235//var/www/html/jili-jiang/" local="130408128240308393" remote="130408137220000000" Dst="0" />
<file name="bg.jpg" server="192.168.1.235//var/www/html/jili-jiang/" local="130408128240338395" remote="130408137220000000" Dst="0" />
<file name="exchangeBg.png" server="192.168.1.235//var/www/html/jili-jiang/" local="130408128240348395" remote="130408137220000000" Dst="0" />
<file name="game.png" server="192.168.1.235//var/www/html/jili-jiang/" local="130408128240478403" remote="130408137220000000" Dst="0" />
<file name="h1.png" server="192.168.1.235//var/www/html/jili-jiang/" local="130408128240488403" remote="130408137220000000" Dst="0" />
<file name="logo.png" server="192.168.1.235//var/www/html/jili-jiang/" local="130408128240498404" remote="130408137220000000" Dst="0" />
<file name="marketActivity.png" server="192.168.1.235//var/www/html/jili-jiang/" local="130408128240518405" remote="130408137220000000" Dst="0" />
<file name="shopping.png" server="192.168.1.235//var/www/html/jili-jiang/" local="130408128240528406" remote="130408137220000000" Dst="0" />
<file name="stepAll.jpg" server="192.168.1.235//var/www/html/jili-jiang/" local="130408128240638412" remote="130408137220000000" Dst="0" />
</dwsync>