<?xml version="1.0" encoding="utf-8" ?>
<dwsync>
<file name="common.css" server="192.168.1.235//var/www/html/jili-amy/" local="130420140007404846" remote="130420138720000000" Dst="0" />
<file name="checkin.css" server="192.168.1.235//var/www/html/jili-amy/" local="130419295998514762" remote="130419525470000000" Dst="0" />
<file name="index.css" server="192.168.1.235//var/www/html/jili-amy/" local="130420140001004480" remote="130420138710000000" Dst="0" />
<file name="categorys.css" server="192.168.1.235//var/www/html/jili-amy/" local="130420140009484965" remote="130420138720000000" Dst="0" />
<file name="reset.css" server="192.168.1.235//var/www/html/jili-amy/" local="130419269077354960" remote="130419525500000000" Dst="0" />
<file name="pageNumber.css" server="192.168.1.235//var/www/html/jili-amy/" local="130419269077324958" remote="130419525500000000" Dst="0" />
<file name="recommend.css" server="192.168.1.235//var/www/html/jili-amy/" local="130420139997844299" remote="130420138710000000" Dst="0" />
<file name="cps.css" server="192.168.1.235//var/www/html/jili-amy/" local="130419518979628553" remote="130419525490000000" Dst="0" />
<file name="screen.css" server="192.168.1.235//var/www/html/jili-amy/" local="130419269077464966" remote="130419525500000000" Dst="0" />
<file name="commodity834.css" server="192.168.1.235//var/www/html/jili-amy/" local="130420106958174538" remote="130420105670000000" Dst="0" />
<file name="shopList.css" server="192.168.1.235//var/www/html/jili-amy/" local="130419269077624976" remote="130419525500000000" Dst="0" />
<file name="commodity930.css" server="192.168.1.235//var/www/html/jili-amy/" local="130420141249005861" remote="130420139960000000" Dst="0" />
<file name="shopMore.css" server="192.168.1.235//var/www/html/jili-amy/" local="130419312679328850" remote="130419525500000000" Dst="0" />
<file name="searchShop.css" server="192.168.1.235//var/www/html/jili-amy/" local="130419269077484968" remote="130419525500000000" Dst="0" />
<file name="categorysFilter.css" server="192.168.1.235//var/www/html/jili-amy/" local="130419269077214952" remote="130419525450000000" Dst="0" />
<file name=".DS_Store" server="192.168.1.235//var/www/html/jili-amy/" local="130419269098736183" remote="130419525250000000" Dst="0" />
</dwsync>